wodds_py/__init__.py
wodds_py/utils.py
wodds_py-0.1.2.dist-info/LICENSE
wodds_py-0.1.2.dist-info/WHEEL
wodds_py-0.1.2.dist-info/METADATA
wodds_py-0.1.2.dist-info/RECORD
